smda/Disassembler.py
smda/DisassemblyResult.py
smda/DisassemblyStatistics.py
smda/SmdaConfig.py
smda/__init__.py
smda/cil/CilDisassembler.py
smda/cil/CilInstructionEscaper.py
smda/cil/FunctionAnalysisState.py
smda/cil/__init__.py
smda/common/BasicBlock.py
smda/common/BinaryInfo.py
smda/common/BlockLocator.py
smda/common/CodeXref.py
smda/common/DominatorTree.py
smda/common/SmdaBasicBlock.py
smda/common/SmdaFunction.py
smda/common/SmdaInstruction.py
smda/common/SmdaReport.py
smda/common/TailcallAnalyzer.py
smda/common/Tarjan.py
smda/common/__init__.py
smda/common/labelprovider/AbstractLabelProvider.py
smda/common/labelprovider/CilSymbolProvider.py
smda/common/labelprovider/DelphiKbSymbolProvider.py
smda/common/labelprovider/DelphiReSymProvider.py
smda/common/labelprovider/ElfApiResolver.py
smda/common/labelprovider/ElfSymbolProvider.py
smda/common/labelprovider/GoLabelProvider.py
smda/common/labelprovider/OrdinalHelper.py
smda/common/labelprovider/PdbSymbolProvider.py
smda/common/labelprovider/PeSymbolProvider.py
smda/common/labelprovider/RustSymbolProvider.py
smda/common/labelprovider/WinApiResolver.py
smda/common/labelprovider/__init__.py
smda/common/labelprovider/rust_demangler/__init__.py
smda/common/labelprovider/rust_demangler/main.py
smda/common/labelprovider/rust_demangler/rust.py
smda/common/labelprovider/rust_demangler/rust_legacy.py
smda/common/labelprovider/rust_demangler/rust_v0.py
smda/common/labelprovider/rust_demangler/utils.py
smda/ida/BackendInterface.py
smda/ida/IdaExporter.py
smda/ida/IdaInterface.py
smda/ida/__init__.py
smda/intel/BitnessAnalyzer.py
smda/intel/FunctionAnalysisState.py
smda/intel/FunctionCandidate.py
smda/intel/FunctionCandidateManager.py
smda/intel/IndirectCallAnalyzer.py
smda/intel/IntelDisassembler.py
smda/intel/IntelInstructionEscaper.py
smda/intel/JumpTableAnalyzer.py
smda/intel/LanguageAnalyzer.py
smda/intel/MnemonicTfIdf.py
smda/intel/__init__.py
smda/intel/definitions.py
smda/utility/BracketQueue.py
smda-2.5.0.dist-info/licenses/LICENSE
smda-2.5.0.dist-info/METADATA
smda-2.5.0.dist-info/WHEEL
smda-2.5.0.dist-info/top_level.txt
smda-2.5.0.dist-info/RECORD
