Metadata-Version: 2.4
Name: smda
Version: 2.5.0
Summary: A recursive disassmbler optimized for CFG recovery from memory dumps. Based on capstone.
Home-page: https://github.com/danielplohmann/smda
Author: Daniel Plohmann
Author-email: daniel.plohmann@mailbox.org
License: BSD 2-Clause
Classifier: Development Status :: 4 - Beta
Classifier: License :: OSI Approved :: BSD License
Classifier: Operating System :: OS Independent
Classifier: Programming Language :: Python :: 2.7
Classifier: Programming Language :: Python :: 3
Classifier: Topic :: Security
Classifier: Topic :: Software Development :: Disassemblers
License-File: LICENSE
Requires-Dist: capstone
Requires-Dist: dncil
Requires-Dist: dnfile
Requires-Dist: lief>=0.16.0
Dynamic: author
Dynamic: author-email
Dynamic: classifier
Dynamic: description
Dynamic: description-content-type
Dynamic: home-page
Dynamic: license
Dynamic: license-file
Dynamic: requires-dist
Dynamic: summary
